facerec/__init__.py
facerec/dataset.py
facerec/enrollment.py
facerec/evaluate.py
facerec/face_detection.py
facerec/feature_extraction.py
facerec/scoring.py
facerec/configs/baseline_config.yaml
facerec/script/__init__.py
facerec/script/baseline_detection.py
facerec/script/baseline_recognition.py
facerec/script/evaluation.py
facerec/script/scoring.py
challenge.uccs-3.2.1.dist-info/LICENSE
challenge.uccs-3.2.1.dist-info/METADATA
challenge.uccs-3.2.1.dist-info/WHEEL
challenge.uccs-3.2.1.dist-info/entry_points.txt
challenge.uccs-3.2.1.dist-info/top_level.txt
challenge.uccs-3.2.1.dist-info/RECORD
