Metadata-Version: 2.1
Name: challenge.uccs
Version: 3.2.1
Summary: Source code for running the baseline and evaluation of the third UCCS face recognition challenge
Home-page: https://github.com/AIML-IfI/uccs-facerec-challenge
Author: Furkan Kasim
Author-email: furkan.kasim@outlook.com
License: BSD
Classifier: Development Status :: 3 - Alpha
Classifier: Environment :: GPU
Classifier: Intended Audience :: Science/Research
Classifier: License :: OSI Approved :: BSD License
Classifier: Natural Language :: English
Classifier: Programming Language :: Python
Classifier: Topic :: Scientific/Engineering :: Image Processing
Requires-Python: >=3.10
License-File: LICENSE
Requires-Dist: torch >=2.1
Requires-Dist: torchvision
Requires-Dist: pandas >=1.4.3
Requires-Dist: numpy >=1.22.3
Requires-Dist: matplotlib >=3.5.2
Requires-Dist: scikit-learn >=1.1.1
Requires-Dist: scikit-image >=0.19
Requires-Dist: tqdm >=4.64.0
Requires-Dist: opencv-python >=4.8
Requires-Dist: facenet-pytorch ==2.5.3
Requires-Dist: tensorboard
Requires-Dist: gdown ==5.0.1
Requires-Dist: yamlparser
Requires-Dist: termcolor
